[
    {
        "label": "BEST4+ enterocyte",
        "label_num": 5,
        "label_frac": 0.0003794202458643193,
        "label_id": 0,
        "label_ent_mean": 0.0,
        "label_ent_var": 0.0
    },
    {
        "label": "CD11b-positive dendritic cell",
        "label_num": 19,
        "label_frac": 0.0014417969342844135,
        "label_id": 2,
        "label_ent_mean": 0.0,
        "label_ent_var": 0.0
    },
    {
        "label": "Enteric neuron",
        "label_num": 12661,
        "label_frac": 0.9607679465776294,
        "label_id": 3,
        "label_ent_mean": 0.0,
        "label_ent_var": 0.0
    },
    {
        "label": "Enterocyte",
        "label_num": 3,
        "label_frac": 0.0002276521475185916,
        "label_id": 4,
        "label_ent_mean": 0.0,
        "label_ent_var": 0.0
    },
    {
        "label": "Goblet cell",
        "label_num": 11,
        "label_frac": 0.0008347245409015025,
        "label_id": 5,
        "label_ent_mean": 0.0,
        "label_ent_var": 0.0
    },
    {
        "label": "Macrophage",
        "label_num": 10,
        "label_frac": 0.0007588404917286386,
        "label_id": 7,
        "label_ent_mean": 0.0,
        "label_ent_var": 0.0
    },
    {
        "label": "Monocyte",
        "label_num": 98,
        "label_frac": 0.007436636818940658,
        "label_id": 8,
        "label_ent_mean": 0.0,
        "label_ent_var": 0.0
    },
    {
        "label": "Paneth cell",
        "label_num": 1,
        "label_frac": 7.588404917286387e-05,
        "label_id": 9,
        "label_ent_mean": 0.0,
        "label_ent_var": NaN
    },
    {
        "label": "Stem cell",
        "label_num": 72,
        "label_frac": 0.005463651540446198,
        "label_id": 10,
        "label_ent_mean": 0.0,
        "label_ent_var": 0.0
    },
    {
        "label": "Transit amplifying cell",
        "label_num": 298,
        "label_frac": 0.022613446653513433,
        "label_id": 11,
        "label_ent_mean": 0.0,
        "label_ent_var": 0.0
    }
]