[
    {
        "label": "Enteriendocrine",
        "label_num": 332,
        "label_frac": 0.3408624229979466,
        "label_id": 0,
        "label_ent_mean": 0.0,
        "label_ent_var": 0.0
    },
    {
        "label": "Enterocyte",
        "label_num": 143,
        "label_frac": 0.14681724845995894,
        "label_id": 1,
        "label_ent_mean": 3.0179152272718405e-11,
        "label_ent_var": 1.3024171616168917e-19
    },
    {
        "label": "Goblet",
        "label_num": 6,
        "label_frac": 0.006160164271047228,
        "label_id": 2,
        "label_ent_mean": 0.0,
        "label_ent_var": 0.0
    },
    {
        "label": "Paneth-like",
        "label_num": 250,
        "label_frac": 0.25667351129363447,
        "label_id": 3,
        "label_ent_mean": 0.0,
        "label_ent_var": 0.0
    },
    {
        "label": "TA",
        "label_num": 243,
        "label_frac": 0.24948665297741274,
        "label_id": 5,
        "label_ent_mean": 4.999741293988066e-06,
        "label_ent_var": 2.0243230355942956e-09
    }
]