[
    {
        "label": "endothelial cells",
        "label_num": 409,
        "label_frac": 0.07310098302055407,
        "label_id": 0,
        "label_ent_mean": 0.0,
        "label_ent_var": 0.0
    },
    {
        "label": "granulosa cells",
        "label_num": 1149,
        "label_frac": 0.20536193029490615,
        "label_id": 1,
        "label_ent_mean": 8.328482080407989e-20,
        "label_ent_var": 7.969879221446488e-36
    },
    {
        "label": "monocytes",
        "label_num": 678,
        "label_frac": 0.12117962466487936,
        "label_id": 2,
        "label_ent_mean": 0.0,
        "label_ent_var": 0.0
    },
    {
        "label": "oocytes",
        "label_num": 37,
        "label_frac": 0.006613047363717605,
        "label_id": 3,
        "label_ent_mean": 0.0,
        "label_ent_var": 0.0
    },
    {
        "label": "perivascular cells",
        "label_num": 590,
        "label_frac": 0.10545129579982127,
        "label_id": 4,
        "label_ent_mean": 9.826789896755587e-14,
        "label_ent_var": 4.140811839757556e-24
    },
    {
        "label": "stroma",
        "label_num": 2331,
        "label_frac": 0.4166219839142091,
        "label_id": 5,
        "label_ent_mean": 0.0,
        "label_ent_var": 0.0
    },
    {
        "label": "t cells",
        "label_num": 401,
        "label_frac": 0.07167113494191242,
        "label_id": 6,
        "label_ent_mean": 0.0010162011393720115,
        "label_ent_var": 0.00041409856702005087
    }
]