[
    {
        "label": "MHC class II",
        "label_num": 1,
        "label_frac": 0.0029154518950437317,
        "label_id": 0,
        "label_ent_mean": 0.0,
        "label_ent_var": NaN
    },
    {
        "label": "PSCs",
        "label_num": 7,
        "label_frac": 0.02040816326530612,
        "label_id": 1,
        "label_ent_mean": 0.0,
        "label_ent_var": 0.0
    },
    {
        "label": "acinar cells",
        "label_num": 1,
        "label_frac": 0.0029154518950437317,
        "label_id": 2,
        "label_ent_mean": 0.0,
        "label_ent_var": NaN
    },
    {
        "label": "ductal cells",
        "label_num": 13,
        "label_frac": 0.037900874635568516,
        "label_id": 3,
        "label_ent_mean": 2.79651645399452e-10,
        "label_ent_var": 1.016665556070071e-18
    },
    {
        "label": "mast cells",
        "label_num": 1,
        "label_frac": 0.0029154518950437317,
        "label_id": 5,
        "label_ent_mean": 0.0269218171312182,
        "label_ent_var": NaN
    },
    {
        "label": "unclass endocrine",
        "label_num": 24,
        "label_frac": 0.06997084548104957,
        "label_id": 6,
        "label_ent_mean": 8.106945797079505e-08,
        "label_ent_var": 1.5601487042686006e-13
    },
    {
        "label": "unclass exocrine",
        "label_num": 2,
        "label_frac": 0.0058309037900874635,
        "label_id": 7,
        "label_ent_mean": 0.0,
        "label_ent_var": 0.0
    },
    {
        "label": "\u03b1-cells",
        "label_num": 79,
        "label_frac": 0.2303206997084548,
        "label_id": 8,
        "label_ent_mean": 0.0,
        "label_ent_var": 0.0
    },
    {
        "label": "\u03b2-cells",
        "label_num": 128,
        "label_frac": 0.37317784256559766,
        "label_id": 9,
        "label_ent_mean": 0.0,
        "label_ent_var": 0.0
    },
    {
        "label": "\u03b3-cells",
        "label_num": 2,
        "label_frac": 0.0058309037900874635,
        "label_id": 10,
        "label_ent_mean": 0.0,
        "label_ent_var": 0.0
    },
    {
        "label": "\u03b4-cells",
        "label_num": 81,
        "label_frac": 0.23615160349854228,
        "label_id": 11,
        "label_ent_mean": 4.244656810895844e-07,
        "label_ent_var": 7.2059373269981064e-12
    },
    {
        "label": "\u03b5-cells",
        "label_num": 4,
        "label_frac": 0.011661807580174927,
        "label_id": 12,
        "label_ent_mean": 0.0,
        "label_ent_var": 0.0
    }
]