[
    {
        "label": "B cell DEGs",
        "label_num": 199,
        "label_frac": 0.035862317534690935,
        "label_id": 0,
        "label_ent_mean": 5.1860870811478443e-08,
        "label_ent_var": 5.352204343436463e-13
    },
    {
        "label": "Basophil DEGs",
        "label_num": 341,
        "label_frac": 0.061452513966480445,
        "label_id": 1,
        "label_ent_mean": 8.051675616056598e-06,
        "label_ent_var": 2.2106852757134326e-08
    },
    {
        "label": "Cholangiocyte DEGs",
        "label_num": 2,
        "label_frac": 0.0003604253018561903,
        "label_id": 2,
        "label_ent_mean": 0.0,
        "label_ent_var": 0.0
    },
    {
        "label": "Endothelial DEGs",
        "label_num": 380,
        "label_frac": 0.06848080735267616,
        "label_id": 4,
        "label_ent_mean": 0.0,
        "label_ent_var": 0.0
    },
    {
        "label": "Fibroblast DEGs",
        "label_num": 113,
        "label_frac": 0.020364029554874753,
        "label_id": 5,
        "label_ent_mean": 0.0,
        "label_ent_var": 0.0
    },
    {
        "label": "Hepatocyte DEGs",
        "label_num": 74,
        "label_frac": 0.013335736168679042,
        "label_id": 6,
        "label_ent_mean": 0.0,
        "label_ent_var": 0.0
    },
    {
        "label": "Macrophage DEGs",
        "label_num": 219,
        "label_frac": 0.03946657055325284,
        "label_id": 7,
        "label_ent_mean": 4.5106646653116896e-05,
        "label_ent_var": 4.449235881011595e-08
    },
    {
        "label": "Mig. cDC DEGs",
        "label_num": 157,
        "label_frac": 0.028293386195710937,
        "label_id": 8,
        "label_ent_mean": 0.0,
        "label_ent_var": 0.0
    },
    {
        "label": "Monocyte DEGs",
        "label_num": 1110,
        "label_frac": 0.20003604253018561,
        "label_id": 9,
        "label_ent_mean": 0.0,
        "label_ent_var": 0.0
    },
    {
        "label": "Neutrophil DEGs",
        "label_num": 1523,
        "label_frac": 0.27446386736348893,
        "label_id": 10,
        "label_ent_mean": 0.000350373582740227,
        "label_ent_var": 0.00018172783676714756
    },
    {
        "label": "Plasma cell DEGs",
        "label_num": 1179,
        "label_frac": 0.2124707154442242,
        "label_id": 11,
        "label_ent_mean": 7.312384812613585e-08,
        "label_ent_var": 6.924967752658795e-13
    },
    {
        "label": "Res. NK cell DEGs",
        "label_num": 11,
        "label_frac": 0.0019823391602090466,
        "label_id": 12,
        "label_ent_mean": 0.0,
        "label_ent_var": 0.0
    },
    {
        "label": "cDC1 DEGs",
        "label_num": 95,
        "label_frac": 0.01712020183816904,
        "label_id": 14,
        "label_ent_mean": 6.06877454508e-05,
        "label_ent_var": 3.498852325506044e-07
    },
    {
        "label": "cDC2 DEGs",
        "label_num": 6,
        "label_frac": 0.001081275905568571,
        "label_id": 15,
        "label_ent_mean": 4.274999409936239e-27,
        "label_ent_var": 4.366084883378851e-53
    },
    {
        "label": "pDC DEGs",
        "label_num": 140,
        "label_frac": 0.025229771129933323,
        "label_id": 16,
        "label_ent_mean": 0.0,
        "label_ent_var": 0.0
    }
]