[
    {
        "label": "B cells",
        "label_num": 342,
        "label_frac": 0.02073984232868405,
        "label_id": 0,
        "label_ent_mean": 0.0,
        "label_ent_var": 0.0
    },
    {
        "label": "CD",
        "label_num": 399,
        "label_frac": 0.02419648271679806,
        "label_id": 1,
        "label_ent_mean": 0.00176571711668304,
        "label_ent_var": 0.0011376360012210303
    },
    {
        "label": "Cycling cells",
        "label_num": 142,
        "label_frac": 0.008611279563371741,
        "label_id": 2,
        "label_ent_mean": 0.0,
        "label_ent_var": 0.0
    },
    {
        "label": "EC",
        "label_num": 108,
        "label_frac": 0.006549423893268648,
        "label_id": 3,
        "label_ent_mean": 0.0,
        "label_ent_var": 0.0
    },
    {
        "label": "Fibroblast",
        "label_num": 145,
        "label_frac": 0.008793208004851425,
        "label_id": 4,
        "label_ent_mean": 2.212632871156283e-05,
        "label_ent_var": 3.918695139757552e-09
    },
    {
        "label": "LOH (AL)",
        "label_num": 567,
        "label_frac": 0.0343844754396604,
        "label_id": 5,
        "label_ent_mean": 0.0033279641920659,
        "label_ent_var": 0.0007499992479202456
    },
    {
        "label": "LOH (DL)",
        "label_num": 1563,
        "label_frac": 0.0947847180109157,
        "label_id": 6,
        "label_ent_mean": 0.00025508312301576324,
        "label_ent_var": 1.1248896767417272e-05
    },
    {
        "label": "Mast cells",
        "label_num": 156,
        "label_frac": 0.009460278956943602,
        "label_id": 7,
        "label_ent_mean": 1.123921450408636e-24,
        "label_ent_var": 1.970591105634296e-46
    },
    {
        "label": "Mono1",
        "label_num": 3751,
        "label_frac": 0.22747119466343238,
        "label_id": 8,
        "label_ent_mean": 0.0,
        "label_ent_var": 0.0
    },
    {
        "label": "Mono2",
        "label_num": 44,
        "label_frac": 0.0026682838083687084,
        "label_id": 9,
        "label_ent_mean": 4.209793164245551e-06,
        "label_ent_var": 7.797802652133322e-10
    },
    {
        "label": "Myofibroblast",
        "label_num": 47,
        "label_frac": 0.002850212249848393,
        "label_id": 10,
        "label_ent_mean": 0.0,
        "label_ent_var": 0.0
    },
    {
        "label": "PT",
        "label_num": 8892,
        "label_frac": 0.5392359005457853,
        "label_id": 11,
        "label_ent_mean": 0.0,
        "label_ent_var": 0.0
    },
    {
        "label": "Pericyte",
        "label_num": 31,
        "label_frac": 0.0018799272286234082,
        "label_id": 12,
        "label_ent_mean": 1.0505841771466978e-33,
        "label_ent_var": 3.421544399578095e-65
    },
    {
        "label": "Plasma1",
        "label_num": 4,
        "label_frac": 0.00024257125530624622,
        "label_id": 13,
        "label_ent_mean": 0.0,
        "label_ent_var": 0.0
    },
    {
        "label": "Plasma2",
        "label_num": 51,
        "label_frac": 0.003092783505154639,
        "label_id": 14,
        "label_ent_mean": 0.0,
        "label_ent_var": 0.0
    },
    {
        "label": "T cells",
        "label_num": 248,
        "label_frac": 0.015039417828987265,
        "label_id": 15,
        "label_ent_mean": 0.0,
        "label_ent_var": 0.0
    }
]